pkg_depgraph/__init__.py
pkg_depgraph/dnf.py
pkg_depgraph/protocols.py
pkg_depgraph/repo_diff.py
pkg_depgraph-0.0.1.post1.dist-info/COPYING.md
pkg_depgraph-0.0.1.post1.dist-info/METADATA
pkg_depgraph-0.0.1.post1.dist-info/WHEEL
pkg_depgraph-0.0.1.post1.dist-info/top_level.txt
pkg_depgraph-0.0.1.post1.dist-info/RECORD
